<Properties>
  <MonoDevelop.Ide.Workbench ActiveDocument="Engine/MovementUtilities/Movement_Calcuatlor_c#.cs">
    <Files>
      <File FileName="Engine/MovementUtilities/Movement_Calcuatlor_c#.cs" Line="13" Column="13" />
    </Files>
  </MonoDevelop.Ide.Workbench>
  <MonoDevelop.Ide.Workspace ActiveConfiguration="Debug" />
  <MonoDevelop.Ide.DebuggingService.Breakpoints>
    <BreakpointStore />
  </MonoDevelop.Ide.DebuggingService.Breakpoints>
  <MonoDevelop.Ide.DebuggingService.PinnedWatches />
  <MultiItemStartupConfigurations />
</Properties>